{"id":26722690,"node_id":"MDEwOlJlcG9zaXRvcnkyNjcyMjY5MA==","name":"restheart","full_name":"SoftInstigate/restheart","private":false,"owner":{"login":"SoftInstigate","id":9781674,"node_id":"MDEyOk9yZ2FuaXphdGlvbjk3ODE2NzQ=","avatar_url":"https://avatars.githubusercontent.com/u/9781674?v=4","gravatar_id":"","url":"https://api.github.com/users/SoftInstigate","html_url":"https://github.com/SoftInstigate","followers_url":"https://api.github.com/users/SoftInstigate/followers","following_url":"https://api.github.com/users/SoftInstigate/following{/other_user}","gists_url":"https://api.github.com/users/SoftInstigate/gists{/gist_id}","starred_url":"https://api.github.com/users/SoftInstigate/starred{/owner}{/repo}","subscriptions_url":"https://api.github.com/users/SoftInstigate/subscriptions","organizations_url":"https://api.github.com/users/SoftInstigate/orgs","repos_url":"https://api.github.com/users/SoftInstigate/repos","events_url":"https://api.github.com/users/SoftInstigate/events{/privacy}","received_events_url":"https://api.github.com/users/SoftInstigate/received_events","type":"Organization","site_admin":false},"html_url":"https://github.com/SoftInstigate/restheart","description":"RESTHeart - Instant REST, GraphQL and WebSocket API for MongoDB.","fork":false,"url":"https://api.github.com/repos/SoftInstigate/restheart","forks_url":"https://api.github.com/repos/SoftInstigate/restheart/forks","keys_url":"https://api.github.com/repos/SoftInstigate/restheart/keys{/key_id}","collaborators_url":"https://api.github.com/repos/SoftInstigate/restheart/collaborators{/collaborator}","teams_url":"https://api.github.com/repos/SoftInstigate/restheart/teams","hooks_url":"https://api.github.com/repos/SoftInstigate/restheart/hooks","issue_events_url":"https://api.github.com/repos/SoftInstigate/restheart/issues/events{/number}","events_url":"https://api.github.com/repos/SoftInstigate/restheart/events","assignees_url":"https://api.github.com/repos/SoftInstigate/restheart/assignees{/user}","branches_url":"https://api.github.com/repos/SoftInstigate/restheart/branches{/branch}","tags_url":"https://api.github.com/repos/SoftInstigate/restheart/tags","blobs_url":"https://api.github.com/repos/SoftInstigate/restheart/git/blobs{/sha}","git_tags_url":"https://api.github.com/repos/SoftInstigate/restheart/git/tags{/sha}","git_refs_url":"https://api.github.com/repos/SoftInstigate/restheart/git/refs{/sha}","trees_url":"https://api.github.com/repos/SoftInstigate/restheart/git/trees{/sha}","statuses_url":"https://api.github.com/repos/SoftInstigate/restheart/statuses/{sha}","languages_url":"https://api.github.com/repos/SoftInstigate/restheart/languages","stargazers_url":"https://api.github.com/repos/SoftInstigate/restheart/stargazers","contributors_url":"https://api.github.com/repos/SoftInstigate/restheart/contributors","subscribers_url":"https://api.github.com/repos/SoftInstigate/restheart/subscribers","subscription_url":"https://api.github.com/repos/SoftInstigate/restheart/subscription","commits_url":"https://api.github.com/repos/SoftInstigate/restheart/commits{/sha}","git_commits_url":"https://api.github.com/repos/SoftInstigate/restheart/git/commits{/sha}","comments_url":"https://api.github.com/repos/SoftInstigate/restheart/comments{/number}","issue_comment_url":"https://api.github.com/repos/SoftInstigate/restheart/issues/comments{/number}","contents_url":"https://api.github.com/repos/SoftInstigate/restheart/contents/{+path}","compare_url":"https://api.github.com/repos/SoftInstigate/restheart/compare/{base}...{head}","merges_url":"https://api.github.com/repos/SoftInstigate/restheart/merges","archive_url":"https://api.github.com/repos/SoftInstigate/restheart/{archive_format}{/ref}","downloads_url":"https://api.github.com/repos/SoftInstigate/restheart/downloads","issues_url":"https://api.github.com/repos/SoftInstigate/restheart/issues{/number}","pulls_url":"https://api.github.com/repos/SoftInstigate/restheart/pulls{/number}","milestones_url":"https://api.github.com/repos/SoftInstigate/restheart/milestones{/number}","notifications_url":"https://api.github.com/repos/SoftInstigate/restheart/notifications{?since,all,participating}","labels_url":"https://api.github.com/repos/SoftInstigate/restheart/labels{/name}","releases_url":"https://api.github.com/repos/SoftInstigate/restheart/releases{/id}","deployments_url":"https://api.github.com/repos/SoftInstigate/restheart/deployments","created_at":"2014-11-16T18:01:01Z","updated_at":"2021-12-21T10:58:09Z","pushed_at":"2021-12-21T14:20:21Z","git_url":"git://github.com/SoftInstigate/restheart.git","ssh_url":"git@github.com:SoftInstigate/restheart.git","clone_url":"https://github.com/SoftInstigate/restheart.git","svn_url":"https://github.com/SoftInstigate/restheart","homepage":"http://restheart.org/","size":34557,"stargazers_count":713,"watchers_count":713,"language":"Java","has_issues":true,"has_projects":true,"has_downloads":true,"has_wiki":true,"has_pages":true,"forks_count":162,"mirror_url":null,"archived":false,"disabled":false,"open_issues_count":6,"license":{"key":"other","name":"Other","spdx_id":"NOASSERTION","url":null,"node_id":"MDc6TGljZW5zZTA="},"allow_forking":true,"is_template":false,"topics":["data-persistence","database","docker","graphql","java","microservice","mongodb","nosql","rest","rest-api","restheart","restheart-java","webservice","websockets"],"visibility":"public","forks":162,"open_issues":6,"watchers":713,"default_branch":"master","permissions":{"admin":false,"maintain":false,"push":false,"triage":false,"pull":true},"temp_clone_token":"","organization":{"login":"SoftInstigate","id":9781674,"node_id":"MDEyOk9yZ2FuaXphdGlvbjk3ODE2NzQ=","avatar_url":"https://avatars.githubusercontent.com/u/9781674?v=4","gravatar_id":"","url":"https://api.github.com/users/SoftInstigate","html_url":"https://github.com/SoftInstigate","followers_url":"https://api.github.com/users/SoftInstigate/followers","following_url":"https://api.github.com/users/SoftInstigate/following{/other_user}","gists_url":"https://api.github.com/users/SoftInstigate/gists{/gist_id}","starred_url":"https://api.github.com/users/SoftInstigate/starred{/owner}{/repo}","subscriptions_url":"https://api.github.com/users/SoftInstigate/subscriptions","organizations_url":"https://api.github.com/users/SoftInstigate/orgs","repos_url":"https://api.github.com/users/SoftInstigate/repos","events_url":"https://api.github.com/users/SoftInstigate/events{/privacy}","received_events_url":"https://api.github.com/users/SoftInstigate/received_events","type":"Organization","site_admin":false},"network_count":162,"subscribers_count":43}