{"id":23471389,"node_id":"MDEwOlJlcG9zaXRvcnkyMzQ3MTM4OQ==","name":"homebrew-dart","full_name":"dart-lang/homebrew-dart","private":false,"owner":{"login":"dart-lang","id":1609975,"node_id":"MDEyOk9yZ2FuaXphdGlvbjE2MDk5NzU=","avatar_url":"https://avatars.githubusercontent.com/u/1609975?v=4","gravatar_id":"","url":"https://api.github.com/users/dart-lang","html_url":"https://github.com/dart-lang","followers_url":"https://api.github.com/users/dart-lang/followers","following_url":"https://api.github.com/users/dart-lang/following{/other_user}","gists_url":"https://api.github.com/users/dart-lang/gists{/gist_id}","starred_url":"https://api.github.com/users/dart-lang/starred{/owner}{/repo}","subscriptions_url":"https://api.github.com/users/dart-lang/subscriptions","organizations_url":"https://api.github.com/users/dart-lang/orgs","repos_url":"https://api.github.com/users/dart-lang/repos","events_url":"https://api.github.com/users/dart-lang/events{/privacy}","received_events_url":"https://api.github.com/users/dart-lang/received_events","type":"Organization","site_admin":false},"html_url":"https://github.com/dart-lang/homebrew-dart","description":"Dart team's official tap for homebrew.","fork":false,"url":"https://api.github.com/repos/dart-lang/homebrew-dart","forks_url":"https://api.github.com/repos/dart-lang/homebrew-dart/forks","keys_url":"https://api.github.com/repos/dart-lang/homebrew-dart/keys{/key_id}","collaborators_url":"https://api.github.com/repos/dart-lang/homebrew-dart/collaborators{/collaborator}","teams_url":"https://api.github.com/repos/dart-lang/homebrew-dart/teams","hooks_url":"https://api.github.com/repos/dart-lang/homebrew-dart/hooks","issue_events_url":"https://api.github.com/repos/dart-lang/homebrew-dart/issues/events{/number}","events_url":"https://api.github.com/repos/dart-lang/homebrew-dart/events","assignees_url":"https://api.github.com/repos/dart-lang/homebrew-dart/assignees{/user}","branches_url":"https://api.github.com/repos/dart-lang/homebrew-dart/branches{/branch}","tags_url":"https://api.github.com/repos/dart-lang/homebrew-dart/tags","blobs_url":"https://api.github.com/repos/dart-lang/homebrew-dart/git/blobs{/sha}","git_tags_url":"https://api.github.com/repos/dart-lang/homebrew-dart/git/tags{/sha}","git_refs_url":"https://api.github.com/repos/dart-lang/homebrew-dart/git/refs{/sha}","trees_url":"https://api.github.com/repos/dart-lang/homebrew-dart/git/trees{/sha}","statuses_url":"https://api.github.com/repos/dart-lang/homebrew-dart/statuses/{sha}","languages_url":"https://api.github.com/repos/dart-lang/homebrew-dart/languages","stargazers_url":"https://api.github.com/repos/dart-lang/homebrew-dart/stargazers","contributors_url":"https://api.github.com/repos/dart-lang/homebrew-dart/contributors","subscribers_url":"https://api.github.com/repos/dart-lang/homebrew-dart/subscribers","subscription_url":"https://api.github.com/repos/dart-lang/homebrew-dart/subscription","commits_url":"https://api.github.com/repos/dart-lang/homebrew-dart/commits{/sha}","git_commits_url":"https://api.github.com/repos/dart-lang/homebrew-dart/git/commits{/sha}","comments_url":"https://api.github.com/repos/dart-lang/homebrew-dart/comments{/number}","issue_comment_url":"https://api.github.com/repos/dart-lang/homebrew-dart/issues/comments{/number}","contents_url":"https://api.github.com/repos/dart-lang/homebrew-dart/contents/{+path}","compare_url":"https://api.github.com/repos/dart-lang/homebrew-dart/compare/{base}...{head}","merges_url":"https://api.github.com/repos/dart-lang/homebrew-dart/merges","archive_url":"https://api.github.com/repos/dart-lang/homebrew-dart/{archive_format}{/ref}","downloads_url":"https://api.github.com/repos/dart-lang/homebrew-dart/downloads","issues_url":"https://api.github.com/repos/dart-lang/homebrew-dart/issues{/number}","pulls_url":"https://api.github.com/repos/dart-lang/homebrew-dart/pulls{/number}","milestones_url":"https://api.github.com/repos/dart-lang/homebrew-dart/milestones{/number}","notifications_url":"https://api.github.com/repos/dart-lang/homebrew-dart/notifications{?since,all,participating}","labels_url":"https://api.github.com/repos/dart-lang/homebrew-dart/labels{/name}","releases_url":"https://api.github.com/repos/dart-lang/homebrew-dart/releases{/id}","deployments_url":"https://api.github.com/repos/dart-lang/homebrew-dart/deployments","created_at":"2014-08-29T17:09:29Z","updated_at":"2021-12-23T16:53:29Z","pushed_at":"2021-12-23T16:53:26Z","git_url":"git://github.com/dart-lang/homebrew-dart.git","ssh_url":"git@github.com:dart-lang/homebrew-dart.git","clone_url":"https://github.com/dart-lang/homebrew-dart.git","svn_url":"https://github.com/dart-lang/homebrew-dart","homepage":null,"size":631,"stargazers_count":97,"watchers_count":97,"language":"Ruby","has_issues":true,"has_projects":true,"has_downloads":true,"has_wiki":true,"has_pages":false,"forks_count":49,"mirror_url":null,"archived":false,"disabled":false,"open_issues_count":5,"license":{"key":"bsd-3-clause","name":"BSD 3-Clause \"New\" or \"Revised\" License","spdx_id":"BSD-3-Clause","url":"https://api.github.com/licenses/bsd-3-clause","node_id":"MDc6TGljZW5zZTU="},"allow_forking":true,"is_template":false,"topics":[],"visibility":"public","forks":49,"open_issues":5,"watchers":97,"default_branch":"master","permissions":{"admin":false,"maintain":false,"push":false,"triage":false,"pull":true},"temp_clone_token":"","organization":{"login":"dart-lang","id":1609975,"node_id":"MDEyOk9yZ2FuaXphdGlvbjE2MDk5NzU=","avatar_url":"https://avatars.githubusercontent.com/u/1609975?v=4","gravatar_id":"","url":"https://api.github.com/users/dart-lang","html_url":"https://github.com/dart-lang","followers_url":"https://api.github.com/users/dart-lang/followers","following_url":"https://api.github.com/users/dart-lang/following{/other_user}","gists_url":"https://api.github.com/users/dart-lang/gists{/gist_id}","starred_url":"https://api.github.com/users/dart-lang/starred{/owner}{/repo}","subscriptions_url":"https://api.github.com/users/dart-lang/subscriptions","organizations_url":"https://api.github.com/users/dart-lang/orgs","repos_url":"https://api.github.com/users/dart-lang/repos","events_url":"https://api.github.com/users/dart-lang/events{/privacy}","received_events_url":"https://api.github.com/users/dart-lang/received_events","type":"Organization","site_admin":false},"network_count":49,"subscribers_count":12}