{"id":21796512,"node_id":"MDEwOlJlcG9zaXRvcnkyMTc5NjUxMg==","name":"Mond","full_name":"Rohansi/Mond","private":false,"owner":{"login":"Rohansi","id":1319884,"node_id":"MDQ6VXNlcjEzMTk4ODQ=","avatar_url":"https://avatars.githubusercontent.com/u/1319884?v=4","gravatar_id":"","url":"https://api.github.com/users/Rohansi","html_url":"https://github.com/Rohansi","followers_url":"https://api.github.com/users/Rohansi/followers","following_url":"https://api.github.com/users/Rohansi/following{/other_user}","gists_url":"https://api.github.com/users/Rohansi/gists{/gist_id}","starred_url":"https://api.github.com/users/Rohansi/starred{/owner}{/repo}","subscriptions_url":"https://api.github.com/users/Rohansi/subscriptions","organizations_url":"https://api.github.com/users/Rohansi/orgs","repos_url":"https://api.github.com/users/Rohansi/repos","events_url":"https://api.github.com/users/Rohansi/events{/privacy}","received_events_url":"https://api.github.com/users/Rohansi/received_events","type":"User","site_admin":false},"html_url":"https://github.com/Rohansi/Mond","description":"A scripting language for .NET Core","fork":false,"url":"https://api.github.com/repos/Rohansi/Mond","forks_url":"https://api.github.com/repos/Rohansi/Mond/forks","keys_url":"https://api.github.com/repos/Rohansi/Mond/keys{/key_id}","collaborators_url":"https://api.github.com/repos/Rohansi/Mond/collaborators{/collaborator}","teams_url":"https://api.github.com/repos/Rohansi/Mond/teams","hooks_url":"https://api.github.com/repos/Rohansi/Mond/hooks","issue_events_url":"https://api.github.com/repos/Rohansi/Mond/issues/events{/number}","events_url":"https://api.github.com/repos/Rohansi/Mond/events","assignees_url":"https://api.github.com/repos/Rohansi/Mond/assignees{/user}","branches_url":"https://api.github.com/repos/Rohansi/Mond/branches{/branch}","tags_url":"https://api.github.com/repos/Rohansi/Mond/tags","blobs_url":"https://api.github.com/repos/Rohansi/Mond/git/blobs{/sha}","git_tags_url":"https://api.github.com/repos/Rohansi/Mond/git/tags{/sha}","git_refs_url":"https://api.github.com/repos/Rohansi/Mond/git/refs{/sha}","trees_url":"https://api.github.com/repos/Rohansi/Mond/git/trees{/sha}","statuses_url":"https://api.github.com/repos/Rohansi/Mond/statuses/{sha}","languages_url":"https://api.github.com/repos/Rohansi/Mond/languages","stargazers_url":"https://api.github.com/repos/Rohansi/Mond/stargazers","contributors_url":"https://api.github.com/repos/Rohansi/Mond/contributors","subscribers_url":"https://api.github.com/repos/Rohansi/Mond/subscribers","subscription_url":"https://api.github.com/repos/Rohansi/Mond/subscription","commits_url":"https://api.github.com/repos/Rohansi/Mond/commits{/sha}","git_commits_url":"https://api.github.com/repos/Rohansi/Mond/git/commits{/sha}","comments_url":"https://api.github.com/repos/Rohansi/Mond/comments{/number}","issue_comment_url":"https://api.github.com/repos/Rohansi/Mond/issues/comments{/number}","contents_url":"https://api.github.com/repos/Rohansi/Mond/contents/{+path}","compare_url":"https://api.github.com/repos/Rohansi/Mond/compare/{base}...{head}","merges_url":"https://api.github.com/repos/Rohansi/Mond/merges","archive_url":"https://api.github.com/repos/Rohansi/Mond/{archive_format}{/ref}","downloads_url":"https://api.github.com/repos/Rohansi/Mond/downloads","issues_url":"https://api.github.com/repos/Rohansi/Mond/issues{/number}","pulls_url":"https://api.github.com/repos/Rohansi/Mond/pulls{/number}","milestones_url":"https://api.github.com/repos/Rohansi/Mond/milestones{/number}","notifications_url":"https://api.github.com/repos/Rohansi/Mond/notifications{?since,all,participating}","labels_url":"https://api.github.com/repos/Rohansi/Mond/labels{/name}","releases_url":"https://api.github.com/repos/Rohansi/Mond/releases{/id}","deployments_url":"https://api.github.com/repos/Rohansi/Mond/deployments","created_at":"2014-07-13T17:53:10Z","updated_at":"2021-12-18T11:46:33Z","pushed_at":"2021-08-12T22:25:13Z","git_url":"git://github.com/Rohansi/Mond.git","ssh_url":"git@github.com:Rohansi/Mond.git","clone_url":"https://github.com/Rohansi/Mond.git","svn_url":"https://github.com/Rohansi/Mond","homepage":"https://rohbot.net/mond/","size":2230,"stargazers_count":255,"watchers_count":255,"language":"C#","has_issues":true,"has_projects":true,"has_downloads":true,"has_wiki":true,"has_pages":false,"forks_count":19,"mirror_url":null,"archived":false,"disabled":false,"open_issues_count":9,"license":{"key":"mit","name":"MIT License","spdx_id":"MIT","url":"https://api.github.com/licenses/mit","node_id":"MDc6TGljZW5zZTEz"},"allow_forking":true,"is_template":false,"topics":["bytecode","c-sharp","compiler","debugger","dotnet","dotnet-core","embedded-scripting-language","hacktoberfest","interpreted-programming-language","interpreter","language","mond","nuget","pratt-parser","programming-language","repl","script-engine","scripting","scripting-language","scripting-languages"],"visibility":"public","forks":19,"open_issues":9,"watchers":255,"default_branch":"master","permissions":{"admin":false,"maintain":false,"push":false,"triage":false,"pull":true},"temp_clone_token":"","network_count":19,"subscribers_count":16}