{"id":15870646,"node_id":"MDEwOlJlcG9zaXRvcnkxNTg3MDY0Ng==","name":"brouter","full_name":"abrensch/brouter","private":false,"owner":{"login":"abrensch","id":5775537,"node_id":"MDQ6VXNlcjU3NzU1Mzc=","avatar_url":"https://avatars.githubusercontent.com/u/5775537?v=4","gravatar_id":"","url":"https://api.github.com/users/abrensch","html_url":"https://github.com/abrensch","followers_url":"https://api.github.com/users/abrensch/followers","following_url":"https://api.github.com/users/abrensch/following{/other_user}","gists_url":"https://api.github.com/users/abrensch/gists{/gist_id}","starred_url":"https://api.github.com/users/abrensch/starred{/owner}{/repo}","subscriptions_url":"https://api.github.com/users/abrensch/subscriptions","organizations_url":"https://api.github.com/users/abrensch/orgs","repos_url":"https://api.github.com/users/abrensch/repos","events_url":"https://api.github.com/users/abrensch/events{/privacy}","received_events_url":"https://api.github.com/users/abrensch/received_events","type":"User","site_admin":false},"html_url":"https://github.com/abrensch/brouter","description":"configurable OSM offline router with elevation awareness, Java + Android","fork":false,"url":"https://api.github.com/repos/abrensch/brouter","forks_url":"https://api.github.com/repos/abrensch/brouter/forks","keys_url":"https://api.github.com/repos/abrensch/brouter/keys{/key_id}","collaborators_url":"https://api.github.com/repos/abrensch/brouter/collaborators{/collaborator}","teams_url":"https://api.github.com/repos/abrensch/brouter/teams","hooks_url":"https://api.github.com/repos/abrensch/brouter/hooks","issue_events_url":"https://api.github.com/repos/abrensch/brouter/issues/events{/number}","events_url":"https://api.github.com/repos/abrensch/brouter/events","assignees_url":"https://api.github.com/repos/abrensch/brouter/assignees{/user}","branches_url":"https://api.github.com/repos/abrensch/brouter/branches{/branch}","tags_url":"https://api.github.com/repos/abrensch/brouter/tags","blobs_url":"https://api.github.com/repos/abrensch/brouter/git/blobs{/sha}","git_tags_url":"https://api.github.com/repos/abrensch/brouter/git/tags{/sha}","git_refs_url":"https://api.github.com/repos/abrensch/brouter/git/refs{/sha}","trees_url":"https://api.github.com/repos/abrensch/brouter/git/trees{/sha}","statuses_url":"https://api.github.com/repos/abrensch/brouter/statuses/{sha}","languages_url":"https://api.github.com/repos/abrensch/brouter/languages","stargazers_url":"https://api.github.com/repos/abrensch/brouter/stargazers","contributors_url":"https://api.github.com/repos/abrensch/brouter/contributors","subscribers_url":"https://api.github.com/repos/abrensch/brouter/subscribers","subscription_url":"https://api.github.com/repos/abrensch/brouter/subscription","commits_url":"https://api.github.com/repos/abrensch/brouter/commits{/sha}","git_commits_url":"https://api.github.com/repos/abrensch/brouter/git/commits{/sha}","comments_url":"https://api.github.com/repos/abrensch/brouter/comments{/number}","issue_comment_url":"https://api.github.com/repos/abrensch/brouter/issues/comments{/number}","contents_url":"https://api.github.com/repos/abrensch/brouter/contents/{+path}","compare_url":"https://api.github.com/repos/abrensch/brouter/compare/{base}...{head}","merges_url":"https://api.github.com/repos/abrensch/brouter/merges","archive_url":"https://api.github.com/repos/abrensch/brouter/{archive_format}{/ref}","downloads_url":"https://api.github.com/repos/abrensch/brouter/downloads","issues_url":"https://api.github.com/repos/abrensch/brouter/issues{/number}","pulls_url":"https://api.github.com/repos/abrensch/brouter/pulls{/number}","milestones_url":"https://api.github.com/repos/abrensch/brouter/milestones{/number}","notifications_url":"https://api.github.com/repos/abrensch/brouter/notifications{?since,all,participating}","labels_url":"https://api.github.com/repos/abrensch/brouter/labels{/name}","releases_url":"https://api.github.com/repos/abrensch/brouter/releases{/id}","deployments_url":"https://api.github.com/repos/abrensch/brouter/deployments","created_at":"2014-01-13T14:36:15Z","updated_at":"2021-12-27T21:25:40Z","pushed_at":"2021-12-27T19:04:25Z","git_url":"git://github.com/abrensch/brouter.git","ssh_url":"git@github.com:abrensch/brouter.git","clone_url":"https://github.com/abrensch/brouter.git","svn_url":"https://github.com/abrensch/brouter","homepage":null,"size":4114,"stargazers_count":264,"watchers_count":264,"language":"Java","has_issues":true,"has_projects":true,"has_downloads":true,"has_wiki":true,"has_pages":false,"forks_count":75,"mirror_url":null,"archived":false,"disabled":false,"open_issues_count":123,"license":{"key":"mit","name":"MIT License","spdx_id":"MIT","url":"https://api.github.com/licenses/mit","node_id":"MDc6TGljZW5zZTEz"},"allow_forking":true,"is_template":false,"topics":[],"visibility":"public","forks":75,"open_issues":123,"watchers":264,"default_branch":"master","permissions":{"admin":false,"maintain":false,"push":false,"triage":false,"pull":true},"temp_clone_token":"","network_count":75,"subscribers_count":35}