{"id":2623389,"node_id":"MDEwOlJlcG9zaXRvcnkyNjIzMzg5","name":"CookMe","full_name":"timbru31/CookMe","private":false,"owner":{"login":"timbru31","id":838003,"node_id":"MDQ6VXNlcjgzODAwMw==","avatar_url":"https://avatars.githubusercontent.com/u/838003?v=4","gravatar_id":"","url":"https://api.github.com/users/timbru31","html_url":"https://github.com/timbru31","followers_url":"https://api.github.com/users/timbru31/followers","following_url":"https://api.github.com/users/timbru31/following{/other_user}","gists_url":"https://api.github.com/users/timbru31/gists{/gist_id}","starred_url":"https://api.github.com/users/timbru31/starred{/owner}{/repo}","subscriptions_url":"https://api.github.com/users/timbru31/subscriptions","organizations_url":"https://api.github.com/users/timbru31/orgs","repos_url":"https://api.github.com/users/timbru31/repos","events_url":"https://api.github.com/users/timbru31/events{/privacy}","received_events_url":"https://api.github.com/users/timbru31/received_events","type":"User","site_admin":false},"html_url":"https://github.com/timbru31/CookMe","description":"🔥 🍖 🥓 CookMe plugin for CraftBukkit/Spigot","fork":false,"url":"https://api.github.com/repos/timbru31/CookMe","forks_url":"https://api.github.com/repos/timbru31/CookMe/forks","keys_url":"https://api.github.com/repos/timbru31/CookMe/keys{/key_id}","collaborators_url":"https://api.github.com/repos/timbru31/CookMe/collaborators{/collaborator}","teams_url":"https://api.github.com/repos/timbru31/CookMe/teams","hooks_url":"https://api.github.com/repos/timbru31/CookMe/hooks","issue_events_url":"https://api.github.com/repos/timbru31/CookMe/issues/events{/number}","events_url":"https://api.github.com/repos/timbru31/CookMe/events","assignees_url":"https://api.github.com/repos/timbru31/CookMe/assignees{/user}","branches_url":"https://api.github.com/repos/timbru31/CookMe/branches{/branch}","tags_url":"https://api.github.com/repos/timbru31/CookMe/tags","blobs_url":"https://api.github.com/repos/timbru31/CookMe/git/blobs{/sha}","git_tags_url":"https://api.github.com/repos/timbru31/CookMe/git/tags{/sha}","git_refs_url":"https://api.github.com/repos/timbru31/CookMe/git/refs{/sha}","trees_url":"https://api.github.com/repos/timbru31/CookMe/git/trees{/sha}","statuses_url":"https://api.github.com/repos/timbru31/CookMe/statuses/{sha}","languages_url":"https://api.github.com/repos/timbru31/CookMe/languages","stargazers_url":"https://api.github.com/repos/timbru31/CookMe/stargazers","contributors_url":"https://api.github.com/repos/timbru31/CookMe/contributors","subscribers_url":"https://api.github.com/repos/timbru31/CookMe/subscribers","subscription_url":"https://api.github.com/repos/timbru31/CookMe/subscription","commits_url":"https://api.github.com/repos/timbru31/CookMe/commits{/sha}","git_commits_url":"https://api.github.com/repos/timbru31/CookMe/git/commits{/sha}","comments_url":"https://api.github.com/repos/timbru31/CookMe/comments{/number}","issue_comment_url":"https://api.github.com/repos/timbru31/CookMe/issues/comments{/number}","contents_url":"https://api.github.com/repos/timbru31/CookMe/contents/{+path}","compare_url":"https://api.github.com/repos/timbru31/CookMe/compare/{base}...{head}","merges_url":"https://api.github.com/repos/timbru31/CookMe/merges","archive_url":"https://api.github.com/repos/timbru31/CookMe/{archive_format}{/ref}","downloads_url":"https://api.github.com/repos/timbru31/CookMe/downloads","issues_url":"https://api.github.com/repos/timbru31/CookMe/issues{/number}","pulls_url":"https://api.github.com/repos/timbru31/CookMe/pulls{/number}","milestones_url":"https://api.github.com/repos/timbru31/CookMe/milestones{/number}","notifications_url":"https://api.github.com/repos/timbru31/CookMe/notifications{?since,all,participating}","labels_url":"https://api.github.com/repos/timbru31/CookMe/labels{/name}","releases_url":"https://api.github.com/repos/timbru31/CookMe/releases{/id}","deployments_url":"https://api.github.com/repos/timbru31/CookMe/deployments","created_at":"2011-10-21T21:56:34Z","updated_at":"2021-12-12T08:50:31Z","pushed_at":"2021-11-03T09:56:50Z","git_url":"git://github.com/timbru31/CookMe.git","ssh_url":"git@github.com:timbru31/CookMe.git","clone_url":"https://github.com/timbru31/CookMe.git","svn_url":"https://github.com/timbru31/CookMe","homepage":"https://dev.bukkit.org/projects/cookme","size":316,"stargazers_count":2,"watchers_count":2,"language":"Java","has_issues":true,"has_projects":false,"has_downloads":true,"has_wiki":false,"has_pages":false,"forks_count":0,"mirror_url":null,"archived":false,"disabled":false,"open_issues_count":2,"license":{"key":"mit","name":"MIT License","spdx_id":"MIT","url":"https://api.github.com/licenses/mit","node_id":"MDc6TGljZW5zZTEz"},"allow_forking":true,"is_template":false,"topics":["bukkit","bukkit-plugin","cooking","craftbukkit","food","java","minecraft","spigot","spigot-plugin","spigotmc"],"visibility":"public","forks":0,"open_issues":2,"watchers":2,"default_branch":"master","permissions":{"admin":false,"maintain":false,"push":false,"triage":false,"pull":true},"temp_clone_token":"","network_count":0,"subscribers_count":1}